{"namedChunkGroups":{"polyfill":{"name":"polyfill","assets":[{"name":"polyfill.js","size":759996}],"filteredAssets":0,"assetsSize":759996,"filteredAuxiliaryAssets":0,"auxiliaryAssetsSize":0},"commons":{"name":"commons","assets":[{"name":"framework.js","size":2669060},{"name":"commons.css","size":19675},{"name":"commons.js","size":2328827}],"filteredAssets":0,"assetsSize":5017562,"filteredAuxiliaryAssets":0,"auxiliaryAssetsSize":0},"component---cache-dev-404-page-js":{"name":"component---cache-dev-404-page-js","assets":[{"name":"component---cache-dev-404-page-js.js","size":77446}],"filteredAssets":0,"assetsSize":77446,"filteredAuxiliaryAssets":0,"auxiliaryAssetsSize":0},"component---src-pages-404-js":{"name":"component---src-pages-404-js","assets":[{"name":"framework.js","size":2669060},{"name":"commons.css","size":19675},{"name":"commons.js","size":2328827},{"name":"component---src-pages-404-js.js","size":765757}],"filteredAssets":0,"assetsSize":5783319,"filteredAuxiliaryAssets":0,"auxiliaryAssetsSize":0},"component---src-templates-author-js":{"name":"component---src-templates-author-js","assets":[{"name":"framework.js","size":2669060},{"name":"commons.css","size":19675},{"name":"commons.js","size":2328827},{"name":"component---src-templates-author-js.js","size":1109000}],"filteredAssets":0,"assetsSize":6126562,"filteredAuxiliaryAssets":0,"auxiliaryAssetsSize":0},"component---src-templates-index-js":{"name":"component---src-templates-index-js","assets":[{"name":"framework.js","size":2669060},{"name":"commons.css","size":19675},{"name":"commons.js","size":2328827},{"name":"component---src-templates-index-js.js","size":1102341}],"filteredAssets":0,"assetsSize":6119903,"filteredAuxiliaryAssets":0,"auxiliaryAssetsSize":0},"component---src-templates-post-js":{"name":"component---src-templates-post-js","assets":[{"name":"framework.js","size":2669060},{"name":"commons.css","size":19675},{"name":"commons.js","size":2328827},{"name":"component---src-templates-post-js.js","size":1104079}],"filteredAssets":0,"assetsSize":6121641,"filteredAuxiliaryAssets":0,"auxiliaryAssetsSize":0},"component---src-templates-tag-js":{"name":"component---src-templates-tag-js","assets":[{"name":"framework.js","size":2669060},{"name":"commons.css","size":19675},{"name":"commons.js","size":2328827},{"name":"component---src-templates-tag-js.js","size":1103772}],"filteredAssets":0,"assetsSize":6121334,"filteredAuxiliaryAssets":0,"auxiliaryAssetsSize":0}},"assetsByChunkName":{"polyfill":["polyfill.js"],"commons":["framework.js","commons.css","commons.js"],"component---cache-dev-404-page-js":["component---cache-dev-404-page-js.js"],"component---src-pages-404-js":["framework.js","commons.css","commons.js","component---src-pages-404-js.js"],"component---src-templates-author-js":["framework.js","commons.css","commons.js","component---src-templates-author-js.js"],"component---src-templates-index-js":["framework.js","commons.css","commons.js","component---src-templates-index-js.js"],"component---src-templates-post-js":["framework.js","commons.css","commons.js","component---src-templates-post-js.js"],"component---src-templates-tag-js":["framework.js","commons.css","commons.js","component---src-templates-tag-js.js"]},"childAssetsByChunkName":{}}